edupsyadmin/__init__.py
edupsyadmin/__main__.py
edupsyadmin/__version__.py
edupsyadmin/cli.py
edupsyadmin/info.py
edupsyadmin/api/__init__.py
edupsyadmin/api/add_convenience_data.py
edupsyadmin/api/cft_report.py
edupsyadmin/api/display_client_details.py
edupsyadmin/api/fill_form.py
edupsyadmin/api/flatten_pdf.py
edupsyadmin/api/lgvt.py
edupsyadmin/api/managers.py
edupsyadmin/api/reports.py
edupsyadmin/api/setup_demo.py
edupsyadmin/api/taetigkeitsbericht_from_db.py
edupsyadmin/core/__init__.py
edupsyadmin/core/academic_year.py
edupsyadmin/core/config.py
edupsyadmin/core/convert_measures.py
edupsyadmin/core/datediff.py
edupsyadmin/core/encrypt.py
edupsyadmin/core/int_from_str.py
edupsyadmin/core/logger.py
edupsyadmin/core/python_type.py
edupsyadmin/core/taetigkeitsbericht_check_key.py
edupsyadmin/data/Faecher_BfsEV.md
edupsyadmin/data/Faecher_BfsKi.md
edupsyadmin/data/Faecher_Faks.md
edupsyadmin/data/sampleconfig.yml
edupsyadmin/data/taetigkeitsbericht_categories.csv
edupsyadmin/db/__init__.py
edupsyadmin/db/clients.py
edupsyadmin/tui/__init__.py
edupsyadmin/tui/clients_overview.py
edupsyadmin/tui/clients_overview_app.py
edupsyadmin/tui/dialogs.py
edupsyadmin/tui/edit_client.py
edupsyadmin/tui/edit_client_app.py
edupsyadmin/tui/editconfig.py
edupsyadmin/tui/editconfig.tcss
edupsyadmin/tui/edupsyadmintui.py
edupsyadmin/tui/edupsyadmintui.tcss
edupsyadmin/tui/fill_form_app.py
edupsyadmin/tui/fill_form_widget.py
edupsyadmin-7.13.3.dist-info/METADATA
edupsyadmin-7.13.3.dist-info/WHEEL
edupsyadmin-7.13.3.dist-info/entry_points.txt
edupsyadmin-7.13.3.dist-info/licenses/LICENSE.txt
edupsyadmin-7.13.3.dist-info/RECORD
