Metadata-Version: 2.4
Name: edupsyadmin
Version: 7.13.3
Summary: edupsyadmin provides tools to help school psychologists with their documentation
Author: Lukas Liebermann
License: MIT
License-File: LICENSE.txt
Requires-Python: >=3.14
Requires-Dist: cryptography>=43.0.3
Requires-Dist: fillpdf>=0.7.3
Requires-Dist: keyring>=25.5.0
Requires-Dist: pandas>=2.2.3
Requires-Dist: platformdirs>=4.3.6
Requires-Dist: pydantic>=2.12.3
Requires-Dist: pypdf>=5.1.0
Requires-Dist: python-liquid>=1.12.1
Requires-Dist: pyyaml>=6.0.2
Requires-Dist: scipy>=1.14.1
Requires-Dist: sqlalchemy>=2.0.36
Requires-Dist: textual>=2.1.2
Provides-Extra: bwbackend
Requires-Dist: bitwarden-keyring>=0.3.1; extra == 'bwbackend'
Provides-Extra: flattenpdf
Requires-Dist: pdf2image>=1.17.0; extra == 'flattenpdf'
Provides-Extra: reportsandtaetigkeitsber
Requires-Dist: dataframe-image>=0.2.6; extra == 'reportsandtaetigkeitsber'
Requires-Dist: fpdf2>=2.8.3; extra == 'reportsandtaetigkeitsber'
Requires-Dist: matplotlib>=3.9.2; extra == 'reportsandtaetigkeitsber'
